gguf_clone/__init__.py
gguf_clone/cli.py
gguf_clone/common.py
gguf_clone/convert.py
gguf_clone/files.py
gguf_clone/gguf_path.py
gguf_clone/main.py
gguf_clone/metadata.py
gguf_clone/params.py
gguf_clone/quantize.py
gguf_clone/resolve.py
gguf_clone/split.py
gguf_clone/vendor_info.py
gguf_clone/_vendor/LLAMA_CPP_LICENSE
gguf_clone/_vendor/__init__.py
gguf_clone/_vendor/gguf/__init__.py
gguf_clone/_vendor/gguf/constants.py
gguf_clone/_vendor/gguf/gguf.py
gguf_clone/_vendor/gguf/gguf_reader.py
gguf_clone/_vendor/gguf/gguf_writer.py
gguf_clone/_vendor/gguf/lazy.py
gguf_clone/_vendor/gguf/metadata.py
gguf_clone/_vendor/gguf/py.typed
gguf_clone/_vendor/gguf/quants.py
gguf_clone/_vendor/gguf/tensor_mapping.py
gguf_clone/_vendor/gguf/utility.py
gguf_clone/_vendor/gguf/vocab.py
gguf_clone/_vendor/gguf/scripts/gguf_convert_endian.py
gguf_clone/_vendor/gguf/scripts/gguf_dump.py
gguf_clone/_vendor/gguf/scripts/gguf_editor_gui.py
gguf_clone/_vendor/gguf/scripts/gguf_hash.py
gguf_clone/_vendor/gguf/scripts/gguf_new_metadata.py
gguf_clone/_vendor/gguf/scripts/gguf_set_metadata.py
gguf_clone/_vendor/llama_cpp/__init__.py
gguf_clone/_vendor/llama_cpp/convert_hf_to_gguf.py
gguf_clone-0.1.1.dist-info/METADATA
gguf_clone-0.1.1.dist-info/WHEEL
gguf_clone-0.1.1.dist-info/entry_points.txt
gguf_clone-0.1.1.dist-info/top_level.txt
gguf_clone-0.1.1.dist-info/RECORD
