Metadata-Version: 2.4
Name: gguf-clone
Version: 0.1.1
Summary: Create optimized quants by using similar GGUFs as templates
Author: spicyneuron
License: MIT
Classifier: Programming Language :: Python :: 3
Classifier: Operating System :: OS Independent
Requires-Python: >=3.9
Requires-Dist: numpy~=1.26.4
Requires-Dist: sentencepiece~=0.2.0
Requires-Dist: transformers<5.0.0,>=4.57.1
Requires-Dist: protobuf<5.0.0,>=4.21.0
Requires-Dist: huggingface-hub>=0.24.0
Requires-Dist: pydantic>=2.0.0
Requires-Dist: pyyaml>=6.0.1
Requires-Dist: torch~=2.6.0
